{
  "sections": {
    "parcours_dossier": {
      "type": "ml-parcours-dossier",
      "blocks": {
        "p1": { "type": "pillar", "settings": { "icon": "D", "title": "DIP", "desc": "Dossier d'Information Produit complet, validé par notre responsable qualifié CPNP." } },
        "p2": { "type": "pillar", "settings": { "icon": "C", "title": "CPNP", "desc": "Notification européenne déposée à votre nom, pour une mise en marché conforme." } },
        "p3": { "type": "pillar", "settings": { "icon": "T", "title": "Tests", "desc": "Stabilité, compatibilité packaging, microbiologie : tout est compris." } },
        "d1": { "type": "doc", "settings": { "title": "Formules & INCI", "body": "Liste complète des ingrédients pour chaque produit, formatée pour l'étiquette et la déclaration CPNP." } },
        "d2": { "type": "doc", "settings": { "title": "Évaluation de la sécurité", "body": "Évaluation par notre responsable qualifié, conforme au règlement (CE) n°1223/2009." } },
        "d3": { "type": "doc", "settings": { "title": "Tests de stabilité", "body": "Tests sur 3 mois en conditions accélérées pour valider la durée de vie minimale." } },
        "d4": { "type": "doc", "settings": { "title": "Compatibilité packaging", "body": "Vérification que la formule reste stable au contact du contenant choisi." } },
        "d5": { "type": "doc", "settings": { "title": "Tests microbiologiques (Challenge Test)", "body": "Vérification de l'efficacité du système conservateur contre les contaminations." } }
      },
      "block_order": ["p1", "p2", "p3", "d1", "d2", "d3", "d4", "d5"]
    }
  },
  "order": ["parcours_dossier"]
}
