[
  {
    "id": 35,
    "name": "mylab_devis_relance_l1",
    "email_from": "\"Service Comptabilité MY.LAB\" <yoann@mylab-shop.com>",
    "reply_to": "yoann@mylab-shop.com",
    "body_html": "<div style=\"font-family: 'DM Sans', Arial, sans-serif; color: #333333; font-size: 14px; line-height: 1.6; max-width: 640px;\">\n<p>Bonjour <t t-out=\"object.partner_id.name\"/>,</p>\n<p>Il y a une semaine, je vous ai transmis le devis <strong><t t-out=\"object.name\"/></strong> pour un montant de <t t-out=\"format_amount(object.amount_total, object.currency_id)\"/> TTC.</p>\n<p>Je voulais simplement m'assurer qu'il vous est bien parvenu et savoir où ça en est de votre côté.</p>\n<p>Vous pouvez consulter et valider votre devis directement via ce lien :</p>\n<p style=\"text-align: center; margin: 24px 0;\">\n  <a t-att-href=\"object.get_portal_url()\" style=\"display: inline-block; background: #1a1a1a; color: #fff; padding: 12px 28px; text-decoration: none; font-weight: 600; letter-spacing: 0.04em; text-transform: uppercase; font-size: 12px;\">Voir mon devis</a>\n</p>\n<p>Si une question reste en suspens, n'hésitez pas à me répondre directement à ce mail.</p>\n<p>Bonne journée,<br/>Service Comptabilité — MY.LAB</p>\n<table cellpadding=\"0\" cellspacing=\"0\" border=\"0\" style=\"font-family: 'DM Sans', Arial, sans-serif; font-size: 11px; color: #333333; line-height: 1.4; margin-top: 24px;\">\n  <tr>\n    <td style=\"padding-right: 12px; border-right: 2px solid #c5a467; vertical-align: top;\">\n      <img src=\"https://cdn.shopify.com/s/files/1/0924/1922/7982/files/Logo-rond-noir-sans-fond.png?v=1773170347\" alt=\"MY.LAB\" width=\"55\" height=\"55\" style=\"border-radius: 50%; display: block;\"/>\n    </td>\n    <td style=\"padding-left: 12px; vertical-align: top;\">\n      <p style=\"margin: 0 0 1px 0; font-size: 13px; font-weight: 700; color: #1a1a1a;\">Service Comptabilité</p>\n      <p style=\"margin: 0 0 6px 0; font-size: 10px; font-weight: 500; color: #c5a467; text-transform: uppercase; letter-spacing: 1px;\">MY.LAB</p>\n      <p style=\"margin: 0 0 2px 0; font-size: 11px;\"><span style=\"color: #999;\">T</span>&nbsp;<a href=\"tel:+33485693347\" style=\"color: #333; text-decoration: none;\">04 85 69 33 47</a></p>\n      <p style=\"margin: 0 0 2px 0; font-size: 11px;\"><span style=\"color: #999;\">E</span>&nbsp;<a href=\"mailto:contact@mylab-shop.com\" style=\"color: #333; text-decoration: none;\">contact@mylab-shop.com</a></p>\n      <p style=\"margin: 0 0 6px 0; font-size: 11px;\"><span style=\"color: #999;\">W</span>&nbsp;<a href=\"https://mylab-shop.com\" style=\"color: #c5a467; text-decoration: none; font-weight: 600;\">mylab-shop.com</a></p>\n      <p style=\"margin: 0; font-size: 9px; color: #999;\">231 Avenue de la Voguette, 84300 Cavaillon — France</p>\n      <p style=\"margin: 5px 0 0 0; padding-top: 5px; border-top: 1px solid #e5e5e5; font-size: 9px; color: #c5a467; font-style: italic;\">SARL STARTEC — SIRET 499 500 668 00059 — TVA FR38499500668</p>\n    </td>\n  </tr>\n</table>\n</div>"
  },
  {
    "id": 36,
    "name": "mylab_devis_relance_l2",
    "email_from": "\"Service Comptabilité MY.LAB\" <yoann@mylab-shop.com>",
    "reply_to": "yoann@mylab-shop.com",
    "body_html": "<div style=\"font-family: 'DM Sans', Arial, sans-serif; color: #333333; font-size: 14px; line-height: 1.6; max-width: 640px;\">\n<p>Bonjour <t t-out=\"object.partner_id.name\"/>,</p>\n<p>Je reviens vers vous concernant le devis <strong><t t-out=\"object.name\"/></strong> que je vous ai envoyé il y a deux semaines.</p>\n<p>Si un point n'est pas clair ou si vous avez besoin d'un ajustement (quantités, gammes, packaging…), je suis disponible pour en discuter de vive voix : <a href=\"https://cal.com/mylab-shop/15min\" style=\"color: #c5a467;\">réservez 15 min</a>.</p>\n<p>Sinon, vous pouvez consulter le devis ici :</p>\n<p style=\"text-align: center; margin: 24px 0;\">\n  <a t-att-href=\"object.get_portal_url()\" style=\"display: inline-block; background: #1a1a1a; color: #fff; padding: 12px 28px; text-decoration: none; font-weight: 600; letter-spacing: 0.04em; text-transform: uppercase; font-size: 12px;\">Voir mon devis</a>\n</p>\n<p>Dans l'attente de votre retour,<br/>Service Comptabilité — MY.LAB</p>\n<table cellpadding=\"0\" cellspacing=\"0\" border=\"0\" style=\"font-family: 'DM Sans', Arial, sans-serif; font-size: 11px; color: #333333; line-height: 1.4; margin-top: 24px;\">\n  <tr>\n    <td style=\"padding-right: 12px; border-right: 2px solid #c5a467; vertical-align: top;\">\n      <img src=\"https://cdn.shopify.com/s/files/1/0924/1922/7982/files/Logo-rond-noir-sans-fond.png?v=1773170347\" alt=\"MY.LAB\" width=\"55\" height=\"55\" style=\"border-radius: 50%; display: block;\"/>\n    </td>\n    <td style=\"padding-left: 12px; vertical-align: top;\">\n      <p style=\"margin: 0 0 1px 0; font-size: 13px; font-weight: 700; color: #1a1a1a;\">Service Comptabilité</p>\n      <p style=\"margin: 0 0 6px 0; font-size: 10px; font-weight: 500; color: #c5a467; text-transform: uppercase; letter-spacing: 1px;\">MY.LAB</p>\n      <p style=\"margin: 0 0 2px 0; font-size: 11px;\"><span style=\"color: #999;\">T</span>&nbsp;<a href=\"tel:+33485693347\" style=\"color: #333; text-decoration: none;\">04 85 69 33 47</a></p>\n      <p style=\"margin: 0 0 2px 0; font-size: 11px;\"><span style=\"color: #999;\">E</span>&nbsp;<a href=\"mailto:contact@mylab-shop.com\" style=\"color: #333; text-decoration: none;\">contact@mylab-shop.com</a></p>\n      <p style=\"margin: 0 0 6px 0; font-size: 11px;\"><span style=\"color: #999;\">W</span>&nbsp;<a href=\"https://mylab-shop.com\" style=\"color: #c5a467; text-decoration: none; font-weight: 600;\">mylab-shop.com</a></p>\n      <p style=\"margin: 0; font-size: 9px; color: #999;\">231 Avenue de la Voguette, 84300 Cavaillon — France</p>\n      <p style=\"margin: 5px 0 0 0; padding-top: 5px; border-top: 1px solid #e5e5e5; font-size: 9px; color: #c5a467; font-style: italic;\">SARL STARTEC — SIRET 499 500 668 00059 — TVA FR38499500668</p>\n    </td>\n  </tr>\n</table>\n</div>"
  },
  {
    "id": 37,
    "name": "mylab_facture_relance_l1",
    "email_from": "\"Service Comptabilité MY.LAB\" <yoann@mylab-shop.com>",
    "reply_to": "yoann@mylab-shop.com",
    "body_html": "<div style=\"font-family: 'DM Sans', Arial, sans-serif; color: #333333; font-size: 14px; line-height: 1.6; max-width: 640px;\">\n<p>Bonjour <t t-out=\"object.partner_id.name\"/>,</p>\n<p>Petit rappel amical : votre facture <strong><t t-out=\"object.name\"/></strong> d'un montant de <strong><t t-out=\"format_amount(object.amount_total, object.currency_id)\"/></strong> était arrivée à échéance le <t t-out=\"format_date(object.invoice_date_due)\"/>.</p>\n<p>Si vous l'avez déjà réglée dans les derniers jours, merci d'ignorer ce message. Sinon, vous pouvez procéder au règlement par virement (IBAN dans la facture jointe) ou directement en ligne :</p>\n<p style=\"text-align: center; margin: 24px 0;\">\n  <a t-att-href=\"object.get_portal_url()\" style=\"display: inline-block; background: #1a1a1a; color: #fff; padding: 12px 28px; text-decoration: none; font-weight: 600; letter-spacing: 0.04em; text-transform: uppercase; font-size: 12px;\">Régler en ligne</a>\n</p>\n<p>Bonne journée,<br/>Service Comptabilité — MY.LAB</p>\n<table cellpadding=\"0\" cellspacing=\"0\" border=\"0\" style=\"font-family: 'DM Sans', Arial, sans-serif; font-size: 11px; color: #333333; line-height: 1.4; margin-top: 24px;\">\n  <tr>\n    <td style=\"padding-right: 12px; border-right: 2px solid #c5a467; vertical-align: top;\">\n      <img src=\"https://cdn.shopify.com/s/files/1/0924/1922/7982/files/Logo-rond-noir-sans-fond.png?v=1773170347\" alt=\"MY.LAB\" width=\"55\" height=\"55\" style=\"border-radius: 50%; display: block;\"/>\n    </td>\n    <td style=\"padding-left: 12px; vertical-align: top;\">\n      <p style=\"margin: 0 0 1px 0; font-size: 13px; font-weight: 700; color: #1a1a1a;\">Service Comptabilité</p>\n      <p style=\"margin: 0 0 6px 0; font-size: 10px; font-weight: 500; color: #c5a467; text-transform: uppercase; letter-spacing: 1px;\">MY.LAB</p>\n      <p style=\"margin: 0 0 2px 0; font-size: 11px;\"><span style=\"color: #999;\">T</span>&nbsp;<a href=\"tel:+33485693347\" style=\"color: #333; text-decoration: none;\">04 85 69 33 47</a></p>\n      <p style=\"margin: 0 0 2px 0; font-size: 11px;\"><span style=\"color: #999;\">E</span>&nbsp;<a href=\"mailto:contact@mylab-shop.com\" style=\"color: #333; text-decoration: none;\">contact@mylab-shop.com</a></p>\n      <p style=\"margin: 0 0 6px 0; font-size: 11px;\"><span style=\"color: #999;\">W</span>&nbsp;<a href=\"https://mylab-shop.com\" style=\"color: #c5a467; text-decoration: none; font-weight: 600;\">mylab-shop.com</a></p>\n      <p style=\"margin: 0; font-size: 9px; color: #999;\">231 Avenue de la Voguette, 84300 Cavaillon — France</p>\n      <p style=\"margin: 5px 0 0 0; padding-top: 5px; border-top: 1px solid #e5e5e5; font-size: 9px; color: #c5a467; font-style: italic;\">SARL STARTEC — SIRET 499 500 668 00059 — TVA FR38499500668</p>\n    </td>\n  </tr>\n</table>\n</div>"
  },
  {
    "id": 38,
    "name": "mylab_facture_relance_l2",
    "email_from": "\"Service Comptabilité MY.LAB\" <yoann@mylab-shop.com>",
    "reply_to": "yoann@mylab-shop.com",
    "body_html": "<div style=\"font-family: 'DM Sans', Arial, sans-serif; color: #333333; font-size: 14px; line-height: 1.6; max-width: 640px;\">\n<p>Bonjour <t t-out=\"object.partner_id.name\"/>,</p>\n<p>Sauf erreur de ma part, votre facture <strong><t t-out=\"object.name\"/></strong> d'un montant de <strong><t t-out=\"format_amount(object.amount_total, object.currency_id)\"/></strong> est toujours en attente de règlement (échéance dépassée depuis le <t t-out=\"format_date(object.invoice_date_due)\"/>).</p>\n<p>Merci de procéder au règlement <strong>sous huitaine</strong>, ou de me revenir si un point bloque ou si vous avez besoin d'un échéancier.</p>\n<p style=\"text-align: center; margin: 24px 0;\">\n  <a t-att-href=\"object.get_portal_url()\" style=\"display: inline-block; background: #1a1a1a; color: #fff; padding: 12px 28px; text-decoration: none; font-weight: 600; letter-spacing: 0.04em; text-transform: uppercase; font-size: 12px;\">Régler maintenant</a>\n</p>\n<p>Cordialement,<br/>Service Comptabilité — MY.LAB</p>\n<table cellpadding=\"0\" cellspacing=\"0\" border=\"0\" style=\"font-family: 'DM Sans', Arial, sans-serif; font-size: 11px; color: #333333; line-height: 1.4; margin-top: 24px;\">\n  <tr>\n    <td style=\"padding-right: 12px; border-right: 2px solid #c5a467; vertical-align: top;\">\n      <img src=\"https://cdn.shopify.com/s/files/1/0924/1922/7982/files/Logo-rond-noir-sans-fond.png?v=1773170347\" alt=\"MY.LAB\" width=\"55\" height=\"55\" style=\"border-radius: 50%; display: block;\"/>\n    </td>\n    <td style=\"padding-left: 12px; vertical-align: top;\">\n      <p style=\"margin: 0 0 1px 0; font-size: 13px; font-weight: 700; color: #1a1a1a;\">Service Comptabilité</p>\n      <p style=\"margin: 0 0 6px 0; font-size: 10px; font-weight: 500; color: #c5a467; text-transform: uppercase; letter-spacing: 1px;\">MY.LAB</p>\n      <p style=\"margin: 0 0 2px 0; font-size: 11px;\"><span style=\"color: #999;\">T</span>&nbsp;<a href=\"tel:+33485693347\" style=\"color: #333; text-decoration: none;\">04 85 69 33 47</a></p>\n      <p style=\"margin: 0 0 2px 0; font-size: 11px;\"><span style=\"color: #999;\">E</span>&nbsp;<a href=\"mailto:contact@mylab-shop.com\" style=\"color: #333; text-decoration: none;\">contact@mylab-shop.com</a></p>\n      <p style=\"margin: 0 0 6px 0; font-size: 11px;\"><span style=\"color: #999;\">W</span>&nbsp;<a href=\"https://mylab-shop.com\" style=\"color: #c5a467; text-decoration: none; font-weight: 600;\">mylab-shop.com</a></p>\n      <p style=\"margin: 0; font-size: 9px; color: #999;\">231 Avenue de la Voguette, 84300 Cavaillon — France</p>\n      <p style=\"margin: 5px 0 0 0; padding-top: 5px; border-top: 1px solid #e5e5e5; font-size: 9px; color: #c5a467; font-style: italic;\">SARL STARTEC — SIRET 499 500 668 00059 — TVA FR38499500668</p>\n    </td>\n  </tr>\n</table>\n</div>"
  },
  {
    "id": 39,
    "name": "mylab_facture_relance_l3",
    "email_from": "\"Service Comptabilité MY.LAB\" <yoann@mylab-shop.com>",
    "reply_to": "yoann@mylab-shop.com",
    "body_html": "<div style=\"font-family: 'DM Sans', Arial, sans-serif; color: #333333; font-size: 14px; line-height: 1.6; max-width: 640px;\">\n<p>Bonjour <t t-out=\"object.partner_id.name\"/>,</p>\n<p>Malgré nos précédentes relances, votre facture <strong><t t-out=\"object.name\"/></strong> d'un montant de <strong><t t-out=\"format_amount(object.amount_total, object.currency_id)\"/></strong> reste impayée à ce jour, soit plus de 30 jours après son échéance (<t t-out=\"format_date(object.invoice_date_due)\"/>).</p>\n<p>Conformément à l'article L441-10 du Code de commerce, je vous mets en demeure de procéder au règlement intégral de cette somme dans un <strong>délai de 8 jours</strong> à réception de la présente.</p>\n<p>À défaut de règlement dans ce délai, je serai contraint de transférer votre dossier à notre service de recouvrement, lequel appliquera de plein droit :</p>\n<ul>\n  <li>des pénalités de retard au taux légal majoré de 10 points,</li>\n  <li>une indemnité forfaitaire pour frais de recouvrement de 40 € (Art. L441-10 II du Code de commerce),</li>\n  <li>les frais réels de recouvrement complémentaires.</li>\n</ul>\n<p>Si vous traversez une difficulté ponctuelle, contactez-moi dès que possible pour étudier ensemble une solution amiable.</p>\n<p>Cordialement,<br/>Service Comptabilité — SARL STARTEC / MY.LAB</p>\n<table cellpadding=\"0\" cellspacing=\"0\" border=\"0\" style=\"font-family: 'DM Sans', Arial, sans-serif; font-size: 11px; color: #333333; line-height: 1.4; margin-top: 24px;\">\n  <tr>\n    <td style=\"padding-right: 12px; border-right: 2px solid #c5a467; vertical-align: top;\">\n      <img src=\"https://cdn.shopify.com/s/files/1/0924/1922/7982/files/Logo-rond-noir-sans-fond.png?v=1773170347\" alt=\"MY.LAB\" width=\"55\" height=\"55\" style=\"border-radius: 50%; display: block;\"/>\n    </td>\n    <td style=\"padding-left: 12px; vertical-align: top;\">\n      <p style=\"margin: 0 0 1px 0; font-size: 13px; font-weight: 700; color: #1a1a1a;\">Service Comptabilité</p>\n      <p style=\"margin: 0 0 6px 0; font-size: 10px; font-weight: 500; color: #c5a467; text-transform: uppercase; letter-spacing: 1px;\">MY.LAB</p>\n      <p style=\"margin: 0 0 2px 0; font-size: 11px;\"><span style=\"color: #999;\">T</span>&nbsp;<a href=\"tel:+33485693347\" style=\"color: #333; text-decoration: none;\">04 85 69 33 47</a></p>\n      <p style=\"margin: 0 0 2px 0; font-size: 11px;\"><span style=\"color: #999;\">E</span>&nbsp;<a href=\"mailto:contact@mylab-shop.com\" style=\"color: #333; text-decoration: none;\">contact@mylab-shop.com</a></p>\n      <p style=\"margin: 0 0 6px 0; font-size: 11px;\"><span style=\"color: #999;\">W</span>&nbsp;<a href=\"https://mylab-shop.com\" style=\"color: #c5a467; text-decoration: none; font-weight: 600;\">mylab-shop.com</a></p>\n      <p style=\"margin: 0; font-size: 9px; color: #999;\">231 Avenue de la Voguette, 84300 Cavaillon — France</p>\n      <p style=\"margin: 5px 0 0 0; padding-top: 5px; border-top: 1px solid #e5e5e5; font-size: 9px; color: #c5a467; font-style: italic;\">SARL STARTEC — SIRET 499 500 668 00059 — TVA FR38499500668</p>\n    </td>\n  </tr>\n</table>\n</div>"
  },
  {
    "id": 20,
    "name": "Credit Note: Sending",
    "email_from": "{{ (object.invoice_user_id.email_formatted or object.company_id.email_formatted or user.email_formatted) }}",
    "reply_to": false,
    "body_html": "<div style=\"margin: 0px; padding: 0px;\"><p style=\"margin: 0px; padding: 0px; font-size: 13px;\">Bonjour <t t-out=\"object.partner_id.name or ''\">Client</t>,<br/><br/>Veuillez trouver ci-joint votre avoir <span style=\"font-weight: bold;\" t-out=\"object.name or ''\">INV/2026/00001</span> d'un montant de <span style=\"font-weight: bold;\" t-out=\"format_amount(object.amount_total, object.currency_id) or ''\">0,00 €</span>.<br/><br/>Cet avoir sera déduit de votre prochaine facture ou remboursé selon votre préférence.<br/><br/>N'hésitez pas à nous contacter si vous avez des questions.<t t-if=\"not is_html_empty(object.invoice_user_id.signature)\" data-o-mail-quote-container=\"1\"><br/><br/><t t-out=\"object.invoice_user_id.signature or ''\" data-o-mail-quote=\"1\">--<br data-o-mail-quote=\"1\"/>Yoann DURAND</t></t><br/><br/></p></div>"
  },
  {
    "id": 18,
    "name": "Invoice: Sending",
    "email_from": "\"Service Comptabilité MY.LAB\" <yoann@mylab-shop.com>",
    "reply_to": "yoann@mylab-shop.com",
    "body_html": "<div style=\"margin: 0px; padding: 0px;\"><p style=\"margin: 0px; padding: 0px; font-size: 13px;\">Bonjour <t t-out=\"object.partner_id.name or ''\">Client</t>,<br/><br/>Veuillez trouver ci-joint votre facture MYLAB n°<span style=\"font-weight: bold;\" t-out=\"object.name or ''\">FAC/2026/00001</span><t t-if=\"object.invoice_origin\"> (réf. <span style=\"font-weight: bold;\" t-out=\"object.invoice_origin or ''\">S00001</span>)</t> d'un montant de <span style=\"font-weight: bold;\" t-out=\"format_amount(object.amount_total, object.currency_id) or ''\">0,00 €</span> TTC.<br/><br/><t t-if=\"object.payment_state in ('paid', 'in_payment')\">✅ Cette facture a déjà été réglée. Merci pour votre paiement.</t><t t-else=\"\">Veuillez utiliser la communication suivante pour votre paiement : <span style=\"font-weight: bold;\" t-out=\"object.payment_reference or ''\">FAC/2026/00001</span><t t-if=\"object.partner_bank_id\"> sur le compte <span style=\"font-weight: bold;\" t-out=\"object.partner_bank_id.acc_number or ''\">FR76 ...</span></t>.</t><br/><br/>Pour toute question, n'hésitez pas à nous contacter.<br/><br/></p><table cellpadding=\"0\" cellspacing=\"0\" border=\"0\" style=\"font-family: 'DM Sans', Arial, sans-serif; font-size: 11px; color: #333333; line-height: 1.4; margin-top: 24px;\">\n  <tr>\n    <td style=\"padding-right: 12px; border-right: 2px solid #c5a467; vertical-align: top;\">\n      <img src=\"https://cdn.shopify.com/s/files/1/0924/1922/7982/files/Logo-rond-noir-sans-fond.png?v=1773170347\" alt=\"MY.LAB\" width=\"55\" height=\"55\" style=\"border-radius: 50%; display: block;\"/>\n    </td>\n    <td style=\"padding-left: 12px; vertical-align: top;\">\n      <p style=\"margin: 0 0 1px 0; font-size: 13px; font-weight: 700; color: #1a1a1a;\">Service Comptabilité</p>\n      <p style=\"margin: 0 0 6px 0; font-size: 10px; font-weight: 500; color: #c5a467; text-transform: uppercase; letter-spacing: 1px;\">MY.LAB</p>\n      <p style=\"margin: 0 0 2px 0; font-size: 11px;\"><span style=\"color: #999;\">T</span>&nbsp;<a href=\"tel:+33485693347\" style=\"color: #333; text-decoration: none;\">04 85 69 33 47</a></p>\n      <p style=\"margin: 0 0 2px 0; font-size: 11px;\"><span style=\"color: #999;\">E</span>&nbsp;<a href=\"mailto:contact@mylab-shop.com\" style=\"color: #333; text-decoration: none;\">contact@mylab-shop.com</a></p>\n      <p style=\"margin: 0 0 6px 0; font-size: 11px;\"><span style=\"color: #999;\">W</span>&nbsp;<a href=\"https://mylab-shop.com\" style=\"color: #c5a467; text-decoration: none; font-weight: 600;\">mylab-shop.com</a></p>\n      <p style=\"margin: 0; font-size: 9px; color: #999;\">231 Avenue de la Voguette, 84300 Cavaillon — France</p>\n      <p style=\"margin: 5px 0 0 0; padding-top: 5px; border-top: 1px solid #e5e5e5; font-size: 9px; color: #c5a467; font-style: italic;\">SARL STARTEC — SIRET 499 500 668 00059 — TVA FR38499500668</p>\n    </td>\n  </tr>\n</table><br/><br/></div>"
  },
  {
    "id": 34,
    "name": "MYLAB - Envoi Devis",
    "email_from": "{{ (object.user_id.email_formatted or object.company_id.email_formatted or user.email_formatted) }}",
    "reply_to": false,
    "body_html": "<div style=\"margin: 0; padding: 0; font-size: 13px; line-height: 1.55; color: #333;\">\n<t t-set=\"partner\" t-value=\"object.partner_id\"/>\n<t t-set=\"contact_partner\" t-value=\"partner\"/>\n<t t-if=\"partner.is_company and partner.child_ids\">\n  <t t-set=\"contacts\" t-value=\"partner.child_ids.filtered(lambda c: c.type == 'contact')[:1]\"/>\n  <t t-if=\"contacts\">\n    <t t-set=\"contact_partner\" t-value=\"contacts[0]\"/>\n  </t>\n</t>\n<t t-set=\"is_person\" t-value=\"not contact_partner.is_company\"/>\n<t t-set=\"full_name\" t-value=\"(contact_partner.name or '').strip() if is_person else ''\"/>\n<t t-set=\"parts\" t-value=\"full_name.split() if full_name else []\"/>\n<t t-set=\"firstname_raw\" t-value=\"parts[0] if parts else ''\"/>\n<t t-set=\"firstname\" t-value=\"firstname_raw.title() if firstname_raw.isupper() else firstname_raw\"/>\n<p style=\"margin: 0 0 1rem 0;\">\n<t t-if=\"firstname\">Bonjour <t t-out=\"firstname\"/>,</t>\n<t t-else=\"\">Bonjour Madame, Monsieur,</t>\n</p>\n<p style=\"margin: 0 0 1rem 0;\">Merci pour votre demande de devis ! Vous trouverez ci-joint votre devis n°<span style=\"font-weight: bold;\" t-out=\"object.name or ''\">S00001</span> d'un montant de <span style=\"font-weight: bold;\" t-out=\"format_amount(object.amount_untaxed, object.currency_id) or ''\">0,00 €</span> HT (<span t-out=\"format_amount(object.amount_total, object.currency_id) or ''\">0,00 €</span> TTC), à valider pour lancer sa préparation.</p>\n<p style=\"margin: 0 0 1rem 0;\">Ce devis est <strong>valable 30 jours</strong> à compter de sa date d'émission. Vous pouvez le consulter et l'accepter en ligne en cliquant sur le bouton « Voir le devis » en pied de mail.</p>\n<h3 style=\"margin: 1.5rem 0 0.6rem 0; font-size: 14px; color: #1a1a1a; font-weight: 700;\">💳 Régler ce devis</h3>\n<p style=\"margin: 0 0 0.6rem 0;\">Deux moyens de paiement à votre disposition :</p>\n<ul style=\"margin: 0 0 1rem 0; padding-left: 1.2rem; line-height: 1.7;\">\n<li><strong>Virement bancaire</strong> sur le compte SARL STARTEC :<br/>IBAN : <span style=\"font-family: monospace; font-weight: 600;\">FR58 3000 2028 8000 0007 1073 R40</span><br/>BIC : <span style=\"font-family: monospace; font-weight: 600;\">CRLYFRPP</span><br/><em>Pensez à indiquer la référence <strong t-out=\"object.name or ''\">S00001</strong> en libellé du virement.</em></li>\n<li><strong>PayPal</strong> directement depuis le devis en ligne (cliquez sur « Voir le devis » puis sur le bouton de paiement).</li>\n</ul>\n<p style=\"margin: 0 0 1rem 0;\">Dès réception de votre règlement, nous préparons votre commande et vous tenons informé(e) de son expédition.</p>\n<p style=\"margin: 1rem 0;\">Pour toute question (modification, ajout d'une référence, conditions volume…), je reste à votre entière disposition.</p>\n<p style=\"margin: 1rem 0 0 0;\">Bien cordialement,</p>\n<t t-if=\"not is_html_empty(object.user_id.signature)\" data-o-mail-quote-container=\"1\"><br/><t t-out=\"object.user_id.signature or ''\" data-o-mail-quote=\"1\">--<br data-o-mail-quote=\"1\"/>Yoann DURAND</t></t>\n</div>"
  }
]